rgptlinux/rgptlinux.py
rgptlinux-0.0.1.dist-info/LICENSE.txt
rgptlinux-0.0.1.dist-info/METADATA
rgptlinux-0.0.1.dist-info/WHEEL
rgptlinux-0.0.1.dist-info/top_level.txt
rgptlinux-0.0.1.dist-info/RECORD
